pdf2dataset/__init__.py
pdf2dataset/__main__.py
pdf2dataset/extract_task.py
pdf2dataset/extraction.py
pdf2dataset/extraction_memory.py
pdf2dataset/pdf_extract_task.py
pdf2dataset/results.py
pdf2dataset/utils.py
pdf2dataset-0.5.3.dist-info/entry_points.txt
pdf2dataset-0.5.3.dist-info/LICENSE
pdf2dataset-0.5.3.dist-info/WHEEL
pdf2dataset-0.5.3.dist-info/METADATA
pdf2dataset-0.5.3.dist-info/RECORD
