Metadata-Version: 2.1
Name: pdf2dataset
Version: 0.5.3
Summary: Easily convert a subdirectory with big volume of PDF documents into a dataset, supports extracting text and images
Home-page: https://github.com/icaropires/pdf2dataset
License: Apache-2.0
Author: Ícaro Pires
Author-email: icaropsa@gmail.com
Requires-Python: >=3.6,<4.0
Classifier: License :: OSI Approved :: Apache Software License
Classifier: Programming Language :: Python :: 3
Classifier: Programming Language :: Python :: 3.6
Classifier: Programming Language :: Python :: 3.7
Classifier: Programming Language :: Python :: 3.8
Requires-Dist: dask[dataframe] (==2.23.0)
Requires-Dist: more-itertools (>=8.4.0,<9.0.0)
Requires-Dist: opencv-python (==4.4.0.42)
Requires-Dist: packaging (>=20.4,<21.0)
Requires-Dist: pandas (>=0.25.0,<0.26.0)
Requires-Dist: pdf2image (>=1.13.1,<2.0.0)
Requires-Dist: pdftotext (==2.1.5)
Requires-Dist: pyarrow (==1.0.0)
Requires-Dist: pytesseract (==0.3.5)
Requires-Dist: ray (==0.8.7)
Requires-Dist: tqdm (>=4.41.0,<5.0.0)
Project-URL: Repository, https://github.com/icaropires/pdf2dataset
